hello/__init__.py
hello/__main__.py
hello/helloserver.py
tsuyo_hello-1.0.0.dist-info/METADATA
tsuyo_hello-1.0.0.dist-info/WHEEL
tsuyo_hello-1.0.0.dist-info/top_level.txt
tsuyo_hello-1.0.0.dist-info/RECORD
