Metadata-Version: 2.1
Name: tsuyo-hello
Version: 1.0.0
Summary: Hello from Python
License: UNKNOWN
Platform: UNKNOWN
Requires-Python: >=3.6
